OCAT/__init__.py
OCAT/example.cpython-37m-darwin.so
OCAT/fast_similarity_matching.py
OCAT/lineage.py
OCAT/marker_gene.py
OCAT/sparse_encoding.py
OCAT/utils.py
OCAT-0.1.87.dist-info/LICENSE
OCAT-0.1.87.dist-info/METADATA
OCAT-0.1.87.dist-info/WHEEL
OCAT-0.1.87.dist-info/top_level.txt
OCAT-0.1.87.dist-info/RECORD
